d_augmentation/__init__.py
d_augmentation/color.py
d_augmentation/geometric.py
d_augmentation/noise.py
d_augmentation/occlusion.py
d_augmentation/utils.py
d_augmentation-0.1.2.dist-info/METADATA
d_augmentation-0.1.2.dist-info/WHEEL
d_augmentation-0.1.2.dist-info/top_level.txt
d_augmentation-0.1.2.dist-info/RECORD
