Metadata-Version: 2.4
Name: d_augmentation
Version: 0.1.2
Summary: Comprehensive image data augmentation library with geometric, color, noise, and occlusion techniques
Author: Divine Gupta
Author-email: guptadivine0611@gmail.com
Requires-Python: >=3.7
Requires-Dist: opencv-python
Requires-Dist: numpy
Dynamic: author
Dynamic: author-email
Dynamic: description
Dynamic: description-content-type
Dynamic: requires-dist
Dynamic: requires-python
Dynamic: summary
